[
  {
    "D": 64,
    "N": 512,
    "Z": 2,
    "H": 16,
    "causal": false,
    "triton_ms": 0.030051991819634517,
    "torch_ms": 0.033039370609551484,
    "triton_mem_mb": 8.454144,
    "torch_mem_mb": 8.455168,
    "triton_bw_gbs": 281.31726012505004,
    "torch_bw_gbs": 255.88090341999305,
    "triton_tflops": 71.45894557967164,
    "torch_tflops": 64.99771661446769,
    "speedup": 1.0994070146114294
  },
  {
    "D": 64,
    "N": 1024,
    "Z": 2,
    "H": 16,
    "causal": false,
    "triton_ms": 0.06929723187707938,
    "torch_ms": 0.07643918840967988,
    "triton_mem_mb": 16.908288,
    "torch_mem_mb": 16.909312,
    "triton_bw_gbs": 243.9965860395724,
    "torch_bw_gbs": 221.19920883224364,
    "triton_tflops": 123.95783149371641,
    "torch_tflops": 112.37605697697613,
    "speedup": 1.1030626525640883
  },
  {
    "D": 64,
    "N": 2048,
    "Z": 2,
    "H": 16,
    "causal": false,
    "triton_ms": 0.20592833330046456,
    "torch_ms": 0.21245057561160047,
    "triton_mem_mb": 33.816576,
    "torch_mem_mb": 33.8176,
    "triton_bw_gbs": 164.21526585493766,
    "torch_bw_gbs": 159.17384974198916,
    "triton_tflops": 166.85289400107277,
    "torch_tflops": 161.7305025843566,
    "speedup": 1.0316723891588997
  },
  {
    "D": 64,
    "N": 4096,
    "Z": 2,
    "H": 16,
    "causal": false,
    "triton_ms": 0.7730434275119105,
    "torch_ms": 0.7932750691588109,
    "triton_mem_mb": 67.633152,
    "torch_mem_mb": 67.634176,
    "triton_bw_gbs": 87.48945996175352,
    "torch_bw_gbs": 85.25813381695987,
    "triton_tflops": 177.78943404816988,
    "torch_tflops": 173.25510256831882,
    "speedup": 1.026171416671916
  },
  {
    "D": 64,
    "N": 8192,
    "Z": 2,
    "H": 16,
    "causal": false,
    "triton_ms": 2.944384053349495,
    "torch_ms": 3.013169603963052,
    "triton_mem_mb": 135.266304,
    "torch_mem_mb": 135.267328,
    "triton_bw_gbs": 45.94044171857361,
    "torch_bw_gbs": 44.89169936604029,
    "triton_tflops": 186.71335122284898,
    "torch_tflops": 182.45100214901186,
    "speedup": 1.0233616095479485
  },
  {
    "D": 64,
    "N": 16384,
    "Z": 1,
    "H": 16,
    "causal": false,
    "triton_ms": 5.84947195649147,
    "torch_ms": 6.10470387339592,
    "triton_mem_mb": 135.266304,
    "torch_mem_mb": 135.267328,
    "triton_bw_gbs": 23.12453243747716,
    "torch_bw_gbs": 22.157717524921345,
    "triton_tflops": 187.9676722880624,
    "torch_tflops": 180.1089210186971,
    "speedup": 1.0436333260169244
  },
  {
    "D": 64,
    "N": 32768,
    "Z": 1,
    "H": 8,
    "causal": false,
    "triton_ms": 11.680256009101868,
    "torch_ms": 12.05299186706543,
    "triton_mem_mb": 135.266304,
    "torch_mem_mb": 135.267328,
    "triton_bw_gbs": 11.58076534406381,
    "torch_bw_gbs": 11.222632977096135,
    "triton_tflops": 188.2684124250706,
    "torch_tflops": 182.446257311497,
    "speedup": 1.031911617148897
  },
  {
    "D": 64,
    "N": 512,
    "Z": 2,
    "H": 16,
    "causal": true,
    "triton_ms": 0.030222688503868757,
    "torch_ms": 0.03538823609842973,
    "triton_mem_mb": 8.454144,
    "torch_mem_mb": 8.455168,
    "triton_bw_gbs": 279.7283901105555,
    "torch_bw_gbs": 238.89701584688848,
    "triton_tflops": 71.05534796234637,
    "torch_tflops": 60.68354585481273,
    "speedup": 1.1709162172617351
  },
  {
    "D": 64,
    "N": 1024,
    "Z": 2,
    "H": 16,
    "causal": true,
    "triton_ms": 0.058054915601494665,
    "torch_ms": 0.0644254643697414,
    "triton_mem_mb": 16.908288,
    "torch_mem_mb": 16.909312,
    "triton_bw_gbs": 291.2464487256043,
    "torch_bw_gbs": 262.44728176055315,
    "triton_tflops": 147.96222685024188,
    "torch_tflops": 133.3313570345706,
    "speedup": 1.1097331501087002
  },
  {
    "D": 64,
    "N": 2048,
    "Z": 2,
    "H": 16,
    "causal": true,
    "triton_ms": 0.1544577664175591,
    "torch_ms": 0.15877389319633184,
    "triton_mem_mb": 33.816576,
    "torch_mem_mb": 33.8176,
    "triton_bw_gbs": 218.9373625187659,
    "torch_bw_gbs": 212.9857454473584,
    "triton_tflops": 222.45393782992002,
    "torch_tflops": 216.40672579283844,
    "speedup": 1.0279437342574578
  },
  {
    "D": 64,
    "N": 4096,
    "Z": 2,
    "H": 16,
    "causal": true,
    "triton_ms": 0.4703704609702795,
    "torch_ms": 0.4773312427249609,
    "triton_mem_mb": 67.633152,
    "torch_mem_mb": 67.634176,
    "triton_bw_gbs": 143.786988367608,
    "torch_bw_gbs": 141.69018481568435,
    "triton_tflops": 292.1929944080483,
    "torch_tflops": 287.9320295218819,
    "speedup": 1.0147985095414425
  },
  {
    "D": 64,
    "N": 8192,
    "Z": 2,
    "H": 16,
    "causal": true,
    "triton_ms": 1.656217592412775,
    "torch_ms": 1.6762500802675884,
    "triton_mem_mb": 135.266304,
    "torch_mem_mb": 135.267328,
    "triton_bw_gbs": 81.67181934285837,
    "torch_bw_gbs": 80.69577779134647,
    "triton_tflops": 331.93453348549247,
    "torch_tflops": 327.9676585013136,
    "speedup": 1.0120953236740047
  },
  {
    "D": 64,
    "N": 16384,
    "Z": 1,
    "H": 16,
    "causal": true,
    "triton_ms": 3.2731983497225006,
    "torch_ms": 3.3121645791190013,
    "triton_mem_mb": 135.266304,
    "torch_mem_mb": 135.267328,
    "triton_bw_gbs": 41.32542227740881,
    "torch_bw_gbs": 40.839245988186775,
    "triton_tflops": 335.9135348058622,
    "torch_tflops": 331.9616527233251,
    "speedup": 1.0119046343157923
  },
  {
    "D": 64,
    "N": 32768,
    "Z": 1,
    "H": 8,
    "causal": true,
    "triton_ms": 6.397474034627279,
    "torch_ms": 6.519369193485805,
    "triton_mem_mb": 135.266304,
    "torch_mem_mb": 135.267328,
    "triton_bw_gbs": 21.143705041685365,
    "torch_bw_gbs": 20.748373038170463,
    "triton_tflops": 343.73304895798873,
    "torch_tflops": 337.3061396414362,
    "speedup": 1.0190536387015798
  },
  {
    "D": 128,
    "N": 512,
    "Z": 2,
    "H": 8,
    "causal": false,
    "triton_ms": 0.03761852713007676,
    "torch_ms": 0.052729048997972885,
    "triton_mem_mb": 8.421376,
    "torch_mem_mb": 25.330688,
    "triton_bw_gbs": 223.86245933767412,
    "torch_bw_gbs": 159.7103714183002,
    "triton_tflops": 57.08579819125997,
    "torch_tflops": 40.72676615280048,
    "speedup": 1.4016776578106633
  },
  {
    "D": 128,
    "N": 1024,
    "Z": 2,
    "H": 8,
    "causal": false,
    "triton_ms": 0.10532773321093117,
    "torch_ms": 0.0835004066288167,
    "triton_mem_mb": 16.842752,
    "torch_mem_mb": 16.843776,
    "triton_bw_gbs": 159.9080459300345,
    "torch_bw_gbs": 201.70862250852107,
    "triton_tflops": 81.55434784490848,
    "torch_tflops": 102.87296719625243,
    "speedup": 0.792767527443103
  },
  {
    "D": 128,
    "N": 2048,
    "Z": 2,
    "H": 8,
    "causal": false,
    "triton_ms": 0.31074953437424624,
    "torch_ms": 0.22614552252112874,
    "triton_mem_mb": 33.685504,
    "torch_mem_mb": 33.686528,
    "triton_bw_gbs": 108.40081890334034,
    "torch_bw_gbs": 148.95498979800837,
    "triton_tflops": 110.57052245368578,
    "torch_tflops": 151.9364079595685,
    "speedup": 0.7277421122336228
  },
  {
    "D": 128,
    "N": 4096,
    "Z": 2,
    "H": 8,
    "causal": false,
    "triton_ms": 0.9779788481778112,
    "torch_ms": 0.6976111458695453,
    "triton_mem_mb": 67.371008,
    "torch_mem_mb": 67.372032,
    "triton_bw_gbs": 68.88800113164712,
    "torch_bw_gbs": 96.57386983980115,
    "triton_tflops": 140.5336666821362,
    "torch_tflops": 197.0137006636952,
    "speedup": 0.7133192575374689
  },
  {
    "D": 128,
    "N": 8192,
    "Z": 2,
    "H": 8,
    "causal": false,
    "triton_ms": 3.458503166834513,
    "torch_ms": 2.780745097569057,
    "triton_mem_mb": 134.742016,
    "torch_mem_mb": 134.74304,
    "triton_bw_gbs": 38.959633546707494,
    "torch_bw_gbs": 48.455364038146556,
    "triton_tflops": 158.95773037304417,
    "torch_tflops": 197.70090195199828,
    "speedup": 0.8040313868251298
  },
  {
    "D": 128,
    "N": 16384,
    "Z": 1,
    "H": 8,
    "causal": false,
    "triton_ms": 6.911999922532302,
    "torch_ms": 5.574997372097439,
    "triton_mem_mb": 134.742016,
    "torch_mem_mb": 134.74304,
    "triton_bw_gbs": 19.493926144408213,
    "torch_bw_gbs": 24.168982872418294,
    "triton_tflops": 159.0728645976575,
    "torch_tflops": 197.22190960645048,
    "speedup": 0.8065679158825808
  },
  {
    "D": 128,
    "N": 32768,
    "Z": 1,
    "H": 4,
    "causal": false,
    "triton_ms": 13.712383815220424,
    "torch_ms": 11.158527851104736,
    "triton_mem_mb": 134.742016,
    "torch_mem_mb": 134.74304,
    "triton_bw_gbs": 9.826301379519403,
    "torch_bw_gbs": 12.075250229953948,
    "triton_tflops": 160.36768553044263,
    "torch_tflops": 197.07109081905355,
    "speedup": 0.8137555075375759
  },
  {
    "D": 128,
    "N": 512,
    "Z": 2,
    "H": 8,
    "causal": true,
    "triton_ms": 0.03741071333761437,
    "torch_ms": 0.048359080737011624,
    "triton_mem_mb": 8.421376,
    "torch_mem_mb": 25.330688,
    "triton_bw_gbs": 225.10599902228483,
    "torch_bw_gbs": 174.14259890086578,
    "triton_tflops": 57.40290564951151,
    "torch_tflops": 44.40704031738187,
    "speedup": 1.2926532648707685
  },
  {
    "D": 128,
    "N": 1024,
    "Z": 2,
    "H": 8,
    "causal": true,
    "triton_ms": 0.09855649365137702,
    "torch_ms": 0.0762905501830044,
    "triton_mem_mb": 16.842752,
    "torch_mem_mb": 16.843776,
    "triton_bw_gbs": 170.8943913891429,
    "torch_bw_gbs": 220.77114347187046,
    "triton_tflops": 87.15746952590558,
    "torch_tflops": 112.59500123402725,
    "speedup": 0.7740793869236691
  },
  {
    "D": 128,
    "N": 2048,
    "Z": 2,
    "H": 8,
    "causal": true,
    "triton_ms": 0.19337588489055635,
    "torch_ms": 0.17738230964716742,
    "triton_mem_mb": 33.685504,
    "torch_mem_mb": 33.686528,
    "triton_bw_gbs": 174.1970257515034,
    "torch_bw_gbs": 189.90340168083338,
    "triton_tflops": 177.68367750428834,
    "torch_tflops": 193.7044254094178,
    "speedup": 0.9172928141870393
  },
  {
    "D": 128,
    "N": 4096,
    "Z": 2,
    "H": 8,
    "causal": true,
    "triton_ms": 0.5657148365588749,
    "torch_ms": 0.5102956227008129,
    "triton_mem_mb": 67.371008,
    "torch_mem_mb": 67.372032,
    "triton_bw_gbs": 119.09004969677612,
    "torch_bw_gbs": 132.02348796062418,
    "triton_tflops": 242.94740846468233,
    "torch_tflops": 269.33202512023246,
    "speedup": 0.902036838568411
  },
  {
    "D": 128,
    "N": 8192,
    "Z": 2,
    "H": 8,
    "causal": true,
    "triton_ms": 1.9248149496443727,
    "torch_ms": 1.636091347174211,
    "triton_mem_mb": 134.742016,
    "torch_mem_mb": 134.74304,
    "triton_bw_gbs": 70.0025818195639,
    "torch_bw_gbs": 82.35604707079517,
    "triton_tflops": 285.6148919612103,
    "torch_tflops": 336.01779927356466,
    "speedup": 0.8499992934263597
  },
  {
    "D": 128,
    "N": 16384,
    "Z": 1,
    "H": 8,
    "causal": true,
    "triton_ms": 3.7091328144073485,
    "torch_ms": 3.2060415983200072,
    "triton_mem_mb": 134.742016,
    "torch_mem_mb": 134.74304,
    "triton_bw_gbs": 36.32709389014674,
    "torch_bw_gbs": 42.02753204156987,
    "triton_tflops": 296.43360936151373,
    "torch_tflops": 342.9498944593087,
    "speedup": 0.8643641947429898
  },
  {
    "D": 128,
    "N": 32768,
    "Z": 1,
    "H": 4,
    "causal": true,
    "triton_ms": 7.202500783480131,
    "torch_ms": 6.515916728973389,
    "triton_mem_mb": 134.742016,
    "torch_mem_mb": 134.74304,
    "triton_bw_gbs": 18.70767113403837,
    "torch_bw_gbs": 20.6789039216634,
    "triton_tflops": 305.31385162716606,
    "torch_tflops": 337.48486161186185,
    "speedup": 0.9046742131453132
  }
]